spidertoolKits/__init__.py
spidertoolKits/multitoolKits.py
spidertoolKits-1.0.0.dist-info/LICENSE.txt
spidertoolKits-1.0.0.dist-info/METADATA
spidertoolKits-1.0.0.dist-info/WHEEL
spidertoolKits-1.0.0.dist-info/top_level.txt
spidertoolKits-1.0.0.dist-info/RECORD
