Metadata-Version: 2.1
Name: spidertoolKits
Version: 1.0.0
Summary: The first package
Author: Karson
License: MIT
License-File: LICENSE.txt
